matnexus/PaperCollector.py
matnexus/TextProcessor.py
matnexus/VecGenerator.py
matnexus/VecVisualizer.py
matnexus/__init__.py
matnexus-0.2.1.dist-info/LICENSE
matnexus-0.2.1.dist-info/METADATA
matnexus-0.2.1.dist-info/WHEEL
matnexus-0.2.1.dist-info/top_level.txt
matnexus-0.2.1.dist-info/RECORD
