Metadata-Version: 2.1
Name: matnexus
Version: 0.2.1
Summary: Library for natural language processing for scientific papers
Home-page: https://gitlab.ruhr-uni-bochum.de/icams-mids/text_mining_tools
Author: Lei Zhang
Author-email: Lei.Zhang-w2i@ruhr-uni-bochum.de
License: GNU GPL v3
Keywords: physics,energy,material science,natural language processing
Classifier: Development Status :: 3 - Alpha
Classifier: Intended Audience :: Developers
Classifier: Topic :: Software Development :: Libraries :: Python Modules
Classifier: License :: OSI Approved :: GNU General Public License v3 (GPLv3)
Classifier: Programming Language :: Python :: 3.10
Requires-Python: >=3.10
License-File: LICENSE
Requires-Dist: colorama
Requires-Dist: matplotlib
Requires-Dist: charset-normalizer
Requires-Dist: plotly
Requires-Dist: numpy
Requires-Dist: seaborn
Requires-Dist: spacy >=3.0.0
Requires-Dist: nltk
Requires-Dist: certifi
Requires-Dist: requests
Requires-Dist: pandas
Requires-Dist: idna
Requires-Dist: packaging
Requires-Dist: scikit-learn
Requires-Dist: gensim
Requires-Dist: black
Requires-Dist: notebook
Requires-Dist: flake8
Requires-Dist: pybliometrics
